DOTA_VERSION
LICENSE
MANIFEST.in
README.md
VERSION
dotabase.png
notes.md
setup.py
dotabase/__init__.py
dotabase/chatwheels.txt
dotabase/dotabase.db
dotabase/dotabase.py
dotabase/schema.sql
dotabase/temp.txt
dotabase.egg-info/PKG-INFO
dotabase.egg-info/SOURCES.txt
dotabase.egg-info/dependency_links.txt
dotabase.egg-info/requires.txt
dotabase.egg-info/top_level.txt
dotabase/__pycache__/__init__.cpython-310.pyc
dotabase/__pycache__/__init__.cpython-37.pyc
dotabase/__pycache__/__init__.cpython-39.pyc
dotabase/__pycache__/dotabase.cpython-310.pyc
dotabase/__pycache__/dotabase.cpython-36.pyc
dotabase/__pycache__/dotabase.cpython-37.pyc
dotabase/__pycache__/dotabase.cpython-39.pyc