Metadata-Version: 2.1
Name: dotabase
Version: 7.8.5
Summary: Dota 2 game data extracted as an SQLite database, with an SQLAlchemy wrapper
Home-page: https://github.com/mdiller/dotabase
Author: Malcolm Diller
Author-email: malcolm@dillerm.io
Keywords: dota dota2 data sqlite
Classifier: License :: OSI Approved :: MIT License
License-File: LICENSE
Requires-Dist: sqlalchemy
